gptclientai/__init__.py
gptclientai/base.py
gptclientai/client.py
gptclientai/Provider/__init__.py
gptclientai/Provider/deepinfra.py
gptclientai/Provider/freechatgpt.py
gptclientai/Provider/helper.py
gptclientai/Provider/koala.py
gptclientai-0.3.0.dist-info/METADATA
gptclientai-0.3.0.dist-info/WHEEL
gptclientai-0.3.0.dist-info/top_level.txt
gptclientai-0.3.0.dist-info/RECORD
