Metadata-Version: 2.1
Name: gptclientai
Version: 0.3.0
Summary: A Python module for easy integration with GPT-based language models, enabling natural language understanding and generation.
Requires-Dist: requests
